{"schema_version":"1.0.0","scraped_at":"2026-06-16T06:38:51.498Z","ticker":"ARTEMISMED.NS","name":"Artemis Medicare Services Ltd","exchange":"National Stock Exchange of India","currency":"INR","country":"India","sector":"N/A","industry":"Health Care and Social Assistance","as_of":null,"price_current":264.3,"shares_outstanding":158.31,"net_debt":554.185,"market_cap":41841.332,"revenue_ttm":10812.424,"net_income_ttm":1036.191,"ebitda_current":2180.057,"eps_ttm":6.5453286,"beta":0.8563086,"is_financial":false,"wacc":{"selected":0.14601417,"after_tax_range":{"low":0.132,"high":0.16},"build":{"long_term_bond_rate":{"low":0.069,"high":0.07400000000000001},"equity_risk_premium":{"low":0.083,"high":0.09300000000000001},"adjusted_beta":{"low":0.82,"high":0.93},"additional_risk_adjustment":{"low":0,"high":0.005},"cost_of_equity":{"low":0.13699999999999998,"high":0.165},"tax_rate":{"low":0.244,"high":0.251},"debt_equity_ratio":{"low":0.06,"high":0.06},"cost_of_debt":{"low":0.079,"high":0.099}},"cost_of_equity_selected":0.15097748,"cost_of_debt_selected":0.08908984,"beta":0.8563086,"market_risk_premium":0.0831},"shared_projection":[{"year":2027,"revenue":14610,"pretax_profit":1881,"net_interest":-374,"da":null,"ebitda":null,"ebit":null,"nopat":null,"tax":468,"capex":null,"change_nwc":-346,"fcf":null,"timing":0.5,"discount_factor":0.934125,"pv_fcf":null},{"year":2028,"revenue":17782,"pretax_profit":2289,"net_interest":-455,"da":null,"ebitda":null,"ebit":null,"nopat":null,"tax":570,"capex":null,"change_nwc":0,"fcf":null,"timing":1.5,"discount_factor":0.815108,"pv_fcf":null},{"year":2029,"revenue":20809,"pretax_profit":2679,"net_interest":-533,"da":null,"ebitda":null,"ebit":null,"nopat":null,"tax":667,"capex":null,"change_nwc":0,"fcf":null,"timing":2.5,"discount_factor":0.711255,"pv_fcf":null},{"year":2030,"revenue":24444,"pretax_profit":3146,"net_interest":-626,"da":null,"ebitda":null,"ebit":null,"nopat":null,"tax":783,"capex":null,"change_nwc":0,"fcf":null,"timing":3.5,"discount_factor":0.620633,"pv_fcf":null},{"year":2031,"revenue":28324,"pretax_profit":3646,"net_interest":-725,"da":null,"ebitda":null,"ebit":null,"nopat":null,"tax":907,"capex":null,"change_nwc":0,"fcf":null,"timing":4.5,"discount_factor":0.541558,"pv_fcf":null},{"year":2032,"revenue":33245,"pretax_profit":4279,"net_interest":-851,"da":null,"ebitda":null,"ebit":null,"nopat":null,"tax":1065,"capex":null,"change_nwc":0,"fcf":null,"timing":5.5,"discount_factor":0.472558,"pv_fcf":null},{"year":2033,"revenue":37904,"pretax_profit":4879,"net_interest":-971,"da":null,"ebitda":null,"ebit":null,"nopat":null,"tax":1214,"capex":null,"change_nwc":0,"fcf":null,"timing":6.5,"discount_factor":0.412349,"pv_fcf":null},{"year":2034,"revenue":42715,"pretax_profit":5498,"net_interest":-1094,"da":null,"ebitda":null,"ebit":null,"nopat":null,"tax":1368,"capex":null,"change_nwc":0,"fcf":null,"timing":7.5,"discount_factor":0.359812,"pv_fcf":null},{"year":2035,"revenue":46980,"pretax_profit":6047,"net_interest":-1203,"da":null,"ebitda":null,"ebit":null,"nopat":null,"tax":1505,"capex":null,"change_nwc":0,"fcf":null,"timing":8.5,"discount_factor":0.313968,"pv_fcf":null},{"year":2036,"revenue":52032,"pretax_profit":6698,"net_interest":-1332,"da":null,"ebitda":null,"ebit":null,"nopat":null,"tax":1667,"capex":null,"change_nwc":0,"fcf":null,"timing":9.5,"discount_factor":0.273965,"pv_fcf":null}],"assumptions_raw":{},"model_tables":{"revenue":{"R1":["(INR in millions)","Projections"],"R2":["","03-2026","03-2027","03-2028","03-2029","03-2030","03-2031","03-2032","03-2033","03-2034","03-2035","03-2036"],"R3":["Revenue","10,812","14,610","17,782","20,809","24,444","28,324","33,245","37,904","42,715","46,980","52,032"],"R4":["% Growth","-","35%","22%","17%","17%","16%","17%","14%","13%","10%","11%"],"R5":["Cost of goods sold","0","0","0","0","0","0","0","0","0","0","0"],"R6":["% of Revenue","0%","0%","0%","0%","0%","0%","0%","0%","0%","0%","0%"],"R7":["Selling, G&A expenses","(1,661)","(2,244)","(2,731)","(3,196)","(3,754)","(4,350)","(5,106)","(5,822)","(6,561)","(7,216)","(7,992)"],"R8":["% of Revenue","15%","15%","15%","15%","15%","15%","15%","15%","15%","15%","15%"],"R9":["Research & Development","0","0","0","0","0","0","0","0","0","0","0"],"R10":["% of Revenue","0%","0%","0%","0%","0%","0%","0%","0%","0%","0%","0%"],"R11":["Net interest & other expenses","(7,760)","(10,485)","(12,762)","(14,935)","(17,543)","(20,328)","(23,859)","(27,204)","(30,656)","(33,717)","(37,343)"],"R12":["% of Revenue","72%","72%","72%","72%","72%","72%","72%","72%","72%","72%","72%"],"R13":["Tax expense","(355)","(468)","(570)","(667)","(783)","(907)","(1,065)","(1,214)","(1,368)","(1,505)","(1,667)"],"R14":["Tax rate","25%","25%","25%","25%","25%","25%","25%","25%","25%","25%","25%"],"R15":["Net profit","1,037","1,413","1,719","2,012","2,363","2,738","3,214","3,665","4,130","4,542","5,031"],"R16":["% Margin","10%","10%","10%","10%","10%","10%","10%","10%","10%","10%","10%"]},"capex":{"R1":["(INR in millions)","Projections"],"R2":["","03-2027","03-2028","03-2029","03-2030","03-2031","03-2032","03-2033","03-2034","03-2035","03-2036"],"R3":["Capex",null,null,null,null,null,null,null,null,null,null],"R4":["% of Revenue",null,null,null,null,null,null,null,null,null,null],"R5":["Historical"],"R6":["","03-2022","03-2023","03-2024","03-2025","03-2026","5y Avg"],"R7":["Capex","1,089","1,465","726","932","1,049","1,052"],"R8":["% of Revenue",null,null,null,null,null,null]},"da":{"R1":["Average useful life (years):",5],"R2":["(INR in millions)","Projections"],"R3":["","03-2027","03-2028","03-2029","03-2030","03-2031","03-2032","03-2033","03-2034","03-2035","03-2036"],"R4":["For CAPEX in"],"R19":["Total depreciation & amortization",null,null,null,null,null,null,null,null,null,null],"R5":[2023,"293","","","","","","","","",""],"R6":[2024,"145","145","","","","","","","",""],"R7":[2025,"186","186","186","","","","","","",""],"R8":[2026,"210","210","210","210","","","","","",""],"R9":["2027",null,null,null,null,null,"","","","",""],"R10":["2028","",null,null,null,null,null,"","","",""],"R11":["2029","","",null,null,null,null,null,"","",""],"R12":["2030","","","",null,null,null,null,null,"",""],"R13":["2031","","","","",null,null,null,null,null,""],"R14":["2032","","","","","",null,null,null,null,null],"R15":["2033","","","","","","",null,null,null,null],"R16":["2034","","","","","","","",null,null,null],"R17":["2035","","","","","","","","",null,null],"R18":["2036","","","","","","","","","",null]},"working_capital":{"R1":["(INR in millions except days)","Projections"],"R2":["","Historical Avg","03-2026","03-2027","03-2028","03-2029","03-2030","03-2031","03-2032","03-2033","03-2034","03-2035","03-2036"],"R3":["Days receivables","0","","0","0","0","0","0","0","0","0","0","0"],"R4":["Trade receivables","","1,196","0","0","0","0","0","0","0","0","0","0"],"R5":["Days payables","5,343","","5,343","7,124","4,156","5,541","5,607","5,101","5,416","5,375","5,297","5,363"],"R6":["Trade payables","","(985)","0","0","0","0","0","0","0","0","0","0"],"R7":["Days inventory","527","","527","703","410","547","553","503","534","530","523","529"],"R8":["Inventory","","134","(0)","(0)","(0)","(0)","(0)","(0)","(0)","(0)","(0)","(0)"],"R9":["Net working capital","","346","0","0","0","0","0","0","0","0","0","0"],"R10":["Change in NWC","","","(346)","0","0","0","0","0","0","0","0","0"]},"terminal":{"typical_5":["Terminal","3,157","(628)",null,null,"786",null,"0",null,5,null],"typical_10":["Terminal","6,081","(1,210)",null,null,"1,513",null,"0",null,10,null],"typical_ebitda_5":["Terminal","3,157","(628)",null,null,"","","","",5,null],"typical_ebitda_10":["Terminal","6,081","(1,210)",null,null,"","","","",10,null],"R1":["(INR in millions)","","2027","2028","2029","2030","2031","2032","2033","2034","2035","2036"],"R2":["Profit before tax","","1,881","2,289","2,679","3,146","3,646","4,279","4,879","5,498","6,047","6,698"],"R3":["(-) Net interest income/expense","","(374)","(455)","(533)","(626)","(725)","(851)","(971)","(1,094)","(1,203)","(1,332)"],"R4":["(+) Depreciation & Armortization","",null,null,null,null,null,null,null,null,null,null],"R5":["EBITDA","",null,null,null,null,null,null,null,null,null,null],"R6":["(-) Tax","","468","570","667","783","907","1,065","1,214","1,368","1,505","1,667"],"R7":["(-) Capex","",null,null,null,null,null,null,null,null,null,null],"R8":["(-) Change in NWC","","(346)","0","0","0","0","0","0","0","0","0"],"R9":["Free Cash Flow (FCF)","",null,null,null,null,null,null,null,null,null,null],"R10":["Peers' EBITDA Multiples","12.3x"],"R11":["Terminal value",[[null,null],[null,null]]],"R12":["WACC / Discount rate","14.6%"],"R13":["Long-term growth rate","4.0%"],"R14":["Timing of FCF (mid year)","",0.5,1.5,2.5,3.5,4.5,5.5,6.5,7.5,8.5,9.5],"R15":["Present value of FCF","",null,null,null,null,null,null,null,null,null,null],"R_end_5":{"R16":["Enterprise value",null],"R17":["Projection period",null,null],"R18":["Terminal value",null,null],"R19":["(-) Current net debt","554"],"R20":["Equity value",null],"R21":["(/) Outstanding shares","158"],"R22":["Fair price","(1,234)"],"TrueFair":[]},"R_end_10":{"R16":["Enterprise value",null],"R17":["Projection period",null,null],"R18":["Terminal value",null,null],"R19":["(-) Current net debt","554"],"R20":["Equity value",null],"R21":["(/) Outstanding shares","158"],"R22":["Fair price","(1,234)"],"TrueFair":[]},"R_end_ebitda_5":{"R16":["Enterprise value",null],"R17":["Projection period",null,""],"R18":["Terminal value",null,""],"R19":["(-) Current net debt","554"],"R20":["Equity value",null],"R21":["(/) Outstanding shares","158"],"R22":["Fair price","(1,234)"],"TrueFair":[]},"R_end_ebitda_10":{"R16":["Enterprise value",null],"R17":["Projection period",null,""],"R18":["Terminal value",null,""],"R19":["(-) Current net debt","554"],"R20":["Equity value",null],"R21":["(/) Outstanding shares","158"],"R22":["Fair price","(1,234)"],"TrueFair":[]}},"wacc":{"R1":["Category","Low","High"],"R2":["Long-term bond rate","6.9%","7.4%"],"R3":["Equity market risk premium","8.3%","9.3%"],"R4":["Adjusted beta",0.82,0.93],"R0":["Additional risk adjustments","0.0%","0.5%"],"R5":["Cost of equity","13.7%","16.5%"],"R6":["Tax rate","24.4%","25.1%"],"R7":["Debt/Equity ratio",0.06,0.06],"R8":["Cost of debt","7.9%","9.9%"],"R9":["After-tax WACC","13.2%","16.0%"],"R10":["Selected WACC","14.6%"]},"eps":[{"2026-03-31":1036.192},{"2025-03-31":826.258},{"2024-03-31":491.406},{"2023-03-31":385.976},{"2022-03-31":318.1},{"2021-03-31":64.9}]},"variants":{"dcf-growth-exit-5y":{"gated_page":false,"data_available":true,"horizon_years":5,"terminal":{"method":"perpetuity_growth","perp_growth":null,"perp_growth_range":null,"exit_multiple":null,"exit_year":5,"terminal_value_pv":null},"wacc_selected":0.146,"enterprise_value":null,"pv_projection":null,"pv_projection_pct":null,"pv_terminal":null,"pv_terminal_pct":null,"net_debt":554,"equity_value":null,"shares_outstanding":158,"fair_value_per_share":0,"fair_value_bridge_rounded":-1234,"upside_pct":-1,"sensitivity":{"fair_price_range":{"low":null,"high":null},"wacc_range":{"low":0.132,"high":0.16},"growth_range":{"low":0.03,"high":0.05},"exit_multiple_range":null,"terminal_value_grid":[[null,null],[null,null]]},"summary_squares":[-100,"264.30","0.00"]},"dcf-growth-exit-10y":{"gated_page":true,"data_available":true,"horizon_years":10,"terminal":{"method":"perpetuity_growth","perp_growth":null,"perp_growth_range":null,"exit_multiple":null,"exit_year":10,"terminal_value_pv":null},"wacc_selected":0.146,"enterprise_value":null,"pv_projection":null,"pv_projection_pct":null,"pv_terminal":null,"pv_terminal_pct":null,"net_debt":554,"equity_value":null,"shares_outstanding":158,"fair_value_per_share":0,"fair_value_bridge_rounded":-1234,"upside_pct":-1,"sensitivity":{"fair_price_range":{"low":null,"high":null},"wacc_range":{"low":0.132,"high":0.16},"growth_range":{"low":0.03,"high":0.05},"exit_multiple_range":null,"terminal_value_grid":[[null,null],[null,null]]},"summary_squares":[-100,"264.30","0.00"]},"dcf-ebitda-exit-5y":{"gated_page":true,"data_available":true,"horizon_years":5,"terminal":{"method":"exit_multiple","perp_growth":null,"perp_growth_range":null,"exit_multiple":12.3,"exit_year":5,"terminal_value_pv":null},"wacc_selected":0.146,"enterprise_value":null,"pv_projection":null,"pv_projection_pct":null,"pv_terminal":null,"pv_terminal_pct":null,"net_debt":554,"equity_value":null,"shares_outstanding":158,"fair_value_per_share":-1234,"fair_value_bridge_rounded":-1234,"upside_pct":-5.6689,"sensitivity":{"fair_price_range":{"low":null,"high":null},"wacc_range":{"low":0.132,"high":0.16},"growth_range":null,"exit_multiple_range":{"low":8.1,"high":12.9},"terminal_value_grid":[[null,null],[null,null]]},"summary_squares":[-123450,"264.30","(1,234.50)"]},"dcf-ebitda-exit-10y":{"gated_page":true,"data_available":true,"horizon_years":10,"terminal":{"method":"exit_multiple","perp_growth":null,"perp_growth_range":null,"exit_multiple":12.3,"exit_year":10,"terminal_value_pv":null},"wacc_selected":0.146,"enterprise_value":null,"pv_projection":null,"pv_projection_pct":null,"pv_terminal":null,"pv_terminal_pct":null,"net_debt":554,"equity_value":null,"shares_outstanding":158,"fair_value_per_share":-1234,"fair_value_bridge_rounded":-1234,"upside_pct":-5.6689,"sensitivity":{"fair_price_range":{"low":null,"high":null},"wacc_range":{"low":0.132,"high":0.16},"growth_range":null,"exit_multiple_range":{"low":8.1,"high":12.9},"terminal_value_grid":[[null,null],[null,null]]},"summary_squares":[-123450,"264.30","(1,234.50)"]}},"other_valuations":{"epv_fair_price":0,"ddm_stable_fair_price":50.863747,"ddm_multi_fair_price":78.032974,"peter_lynch_fair_price":163.63326,"trailing_pe":40.379982,"forward_pe":29.620924,"trailing_ev_ebitda":null},"source":{"carrier":"inline_script:window.most","url":"https://valueinvesting.io/ARTEMISMED.NS/valuation/dcf-growth-exit-5y","fetched_via":"fetch","raw_ref":"https://valueinvesting.io/ARTEMISMED.NS/valuation/dcf-growth-exit-5y"},"_debug":{"html_bytes":114099,"carrier_found":true,"field_count":62,"warnings":["bad JSON in field excel_dict"],"variant_status":{"dcf-growth-exit-5y":"ok","dcf-growth-exit-10y":"ok","dcf-ebitda-exit-5y":"ok","dcf-ebitda-exit-10y":"ok"},"fetch_ms":43,"http_status":200}}