{"schema_version":"1.0.0","scraped_at":"2026-06-15T08:34:24.066Z","ticker":"PNC.NS","name":"Pritish Nandy Communications Ltd","exchange":"National Stock Exchange of India","currency":"INR","country":"India","sector":"Entertainment","industry":"Information","as_of":"2025-12-31","price_current":20.58,"shares_outstanding":14.47,"net_debt":3.193,"market_cap":297.7926,"revenue_ttm":429.606,"net_income_ttm":-110.735,"ebitda_current":17.063,"eps_ttm":-7.65273,"beta":1.8837116,"is_financial":false,"wacc":{"selected":0.12587272,"after_tax_range":{"low":0.111,"high":0.141},"build":{"long_term_bond_rate":{"low":0.069,"high":0.07400000000000001},"equity_risk_premium":{"low":0.083,"high":0.09300000000000001},"adjusted_beta":{"low":0.55,"high":0.72},"additional_risk_adjustment":{"low":0,"high":0.005},"cost_of_equity":{"low":0.114,"high":0.145},"tax_rate":{"low":0.028999999999999998,"high":0.079},"debt_equity_ratio":{"low":0.08,"high":0.08},"cost_of_debt":{"low":0.075,"high":0.08199999999999999}},"cost_of_equity_selected":0.12981443,"cost_of_debt_selected":0.07830221,"beta":1.8837116,"market_risk_premium":0.0831},"shared_projection":[{"year":32026,"revenue":null,"pretax_profit":0,"net_interest":0,"da":1,"ebitda":2,"ebit":1,"nopat":0.96,"tax":0,"capex":1,"change_nwc":21,"fcf":-20,"timing":0.12,"discount_factor":0.985874,"pv_fcf":-20},{"year":2027,"revenue":371,"pretax_profit":14,"net_interest":-1,"da":2,"ebitda":17,"ebit":15,"nopat":14.406,"tax":1,"capex":4,"change_nwc":-133,"fcf":145,"timing":0.75,"discount_factor":0.91492,"pv_fcf":133},{"year":2028,"revenue":392,"pretax_profit":29,"net_interest":-1,"da":3,"ebitda":33,"ebit":30,"nopat":28.812,"tax":1,"capex":4,"change_nwc":61,"fcf":-33,"timing":1.75,"discount_factor":0.812632,"pv_fcf":-27},{"year":2029,"revenue":400,"pretax_profit":44,"net_interest":-1,"da":3,"ebitda":49,"ebit":46,"nopat":44.178,"tax":2,"capex":4,"change_nwc":-12,"fcf":55,"timing":2.75,"discount_factor":0.721779,"pv_fcf":39},{"year":2030,"revenue":412,"pretax_profit":59,"net_interest":-1,"da":4,"ebitda":64,"ebit":60,"nopat":57.624,"tax":2,"capex":5,"change_nwc":-31,"fcf":89,"timing":3.75,"discount_factor":0.641084,"pv_fcf":57},{"year":2031,"revenue":420,"pretax_profit":63,"net_interest":-1,"da":4,"ebitda":69,"ebit":65,"nopat":62.426,"tax":2,"capex":5,"change_nwc":18,"fcf":44,"timing":4.75,"discount_factor":0.569411,"pv_fcf":25},{"year":2032,"revenue":429,"pretax_profit":67,"net_interest":-1,"da":5,"ebitda":73,"ebit":68,"nopat":65.307,"tax":3,"capex":5,"change_nwc":3,"fcf":62,"timing":5.75,"discount_factor":0.505751,"pv_fcf":31},{"year":2033,"revenue":445,"pretax_profit":72,"net_interest":-1,"da":5,"ebitda":78,"ebit":73,"nopat":70.109,"tax":3,"capex":5,"change_nwc":11,"fcf":60,"timing":6.75,"discount_factor":0.449208,"pv_fcf":27},{"year":2034,"revenue":454,"pretax_profit":76,"net_interest":-1,"da":5,"ebitda":82,"ebit":77,"nopat":73.95,"tax":3,"capex":5,"change_nwc":8,"fcf":66,"timing":7.75,"discount_factor":0.398986,"pv_fcf":27},{"year":2035,"revenue":468,"pretax_profit":82,"net_interest":-1,"da":5,"ebitda":88,"ebit":83,"nopat":79.713,"tax":3,"capex":5,"change_nwc":9,"fcf":70,"timing":8.75,"discount_factor":0.35438,"pv_fcf":25}],"assumptions_raw":{"timing_dcf":[0.125,0.75,1.75,2.75,3.75,4.75,5.75,6.75,7.75,8.75],"sga_ratio":-0.13090625576564835,"RD_ratio":0,"interest_other_ratio":-0.09332761976181535,"tax_rate_dcf":0.039603960396039604,"avg_capex_ratio":0.011140557173976426,"past_capex":[-22.3,-0.313,-0.877,-0.438],"dr":[5.886290862053614,4.80668786312825,3.66063364774598,4.784537457642615,4.417286322838948,4.287485809409181,4.496436529963582,4.400402887403904,4.3947750755922215,4.430538164319902],"dp":[30.17237122856342,34.98485965816276,35.193233564467164,33.45015481706445,34.54274934656479,34.3953792426988,34.12942780210935,34.35585213045764,34.29355305842193,34.25961099699631],"di":[811.4102980323668,647.6375683158896,727.073934645526,728.7072669979275,701.1395899864477,718.9735972099671,716.2734847314474,712.1288906426207,715.7919908613452,714.7314554118044],"current_nwc":513.1,"month_left":3,"net_interest_ratio":-0.002481832628064349,"rating":"AAA","current_reporting_period":"2025-12-31","current_FY_end":"2025-03-31","future_cogs_ratio":[-0.7761999988096727,-0.7373899988691891,-0.7005204989257297,-0.6654944739794432,-0.632219750280471,-0.6258975527776662,-0.6196385772498896,-0.6134421914773907,-0.6073077695626168,-0.6012346918669906],"tax_good":1,"int_exp_ttm":1.042,"spread_excel":0.0059,"current_payout_ratio":0,"global_cod":0.0644,"global_cod_no_finance":0.0644,"long_grow_arr":[0.02,0.04],"chosen_tax_arr":[0.31331987891019175,0.01282158719517305,0.0021298434693353863,0.13793103448275862,0.039603960396039604],"cod1_good":"yes","cod2_good":"yes","chosen_6_past_debt":[20.4,13.6,17.764,11.281,22.623],"chosen_6_past_int":[3.4,2.3,1.177,0.977,0.834],"capex_9_years":[0.438,0.877,0.313,22.3,0.1,0.6,17.7,1.8,11.8],"low_add_coe":0,"high_add_coe":0.005,"add_cod2":0,"last_time":1781330482.7510307,"beta_peers":["PNC.NS","CINEVISTA.NS","SILLYMONKS.NS","523277.BO","CREATIVEYE.NS","DQE.NS","512499.BO","RADAAN.NS","532092.BO","521062.BO"],"low_cod":0.07455,"high_cod":0.08205442649562567,"negative_coverage_ratio":0,"coe_arr":[0.11416473172578187,0.14546413042224526],"ddm_future_net_inc":[-0.03703811351983598,13.656546477282262,28.331005115503995,42.34915724259568,56.808652399447205],"avg_long_growth":0.03,"normalized_earning":15.805667864297266,"ttm_net_income_2_periods":[{"2025-12-31":-110.735},{"2025-09-30":-12.471}],"annual_net_debt_2_periods":[{"2025-09-30":3.1930000000000014},{"2025-03-31":-72.89099999999999}],"high_bond_yield":0.07365000000000001,"high_risk_premium":0.0931,"low_beta":0.5477103697446674,"high_beta":0.7176598326771777,"coe":0.12981443107401358,"avg_tax":0.05391290057321009,"tax_arr":[0.028891011115692984,0.0789347900307272],"low_d_e":0.07596887771035585,"effective_interest_rate":0.08205442649562567,"synthetic_ratings_cod":0.07455,"avg_cod":0.07830221324781284,"selected_wacc":0.12587271810780826,"wacc_arr":[0.11121565909500618,0.14052977712061032],"beta":1.88371,"ebit_ttm":13.983000000000013},"model_tables":{"revenue":{"R1":["(INR in millions)","Projections"],"R2":["","03-2025","03-2026","03-2027","03-2028","03-2029","03-2030","03-2031","03-2032","03-2033","03-2034","03-2035"],"R3":["Revenue","336","356","371","392","400","412","420","429","445","454","468"],"R4":["% Growth","42%","6%","4%","6%","2%","3%","2%","2%","4%","2%","3%"],"R5":["Cost of goods sold","(275)","(276)","(273)","(275)","(266)","(261)","(263)","(266)","(273)","(276)","(281)"],"R6":["% of Revenue","82%","78%","74%","70%","67%","63%","63%","62%","61%","61%","60%"],"R7":["Selling, G&A expenses","(44)","(47)","(49)","(51)","(52)","(54)","(55)","(56)","(58)","(59)","(61)"],"R8":["% of Revenue","13%","13%","13%","13%","13%","13%","13%","13%","13%","13%","13%"],"R9":["Research & Development","0","0","0","0","0","0","0","0","0","0","0"],"R10":["% of Revenue","0%","0%","0%","0%","0%","0%","0%","0%","0%","0%","0%"],"R11":["Net interest & other expenses","(31)","(33)","(35)","(37)","(37)","(38)","(39)","(40)","(42)","(42)","(44)"],"R12":["% of Revenue","9%","9%","9%","9%","9%","9%","9%","9%","9%","9%","9%"],"R13":["Tax expense","4","0","(1)","(1)","(2)","(2)","(2)","(3)","(3)","(3)","(3)"],"R14":["Tax rate","-31%","4%","4%","4%","4%","4%","4%","4%","4%","4%","4%"],"R15":["Net profit","(10)","(0)","14","28","42","57","61","64","69","73","78"],"R16":["% Margin","-3%","0%","4%","7%","11%","14%","14%","15%","16%","16%","17%"]},"capex":{"R1":["(INR in millions)","Projections"],"R2":["","03-2026","03-2027","03-2028","03-2029","03-2030","03-2031","03-2032","03-2033","03-2034","03-2035"],"R3":["Capex","4","4","4","4","5","5","5","5","5","5"],"R4":["% of Revenue","1%","1%","1%","1%","1%","1%","1%","1%","1%","1%"],"R5":["Historical"],"R6":["","03-2021","03-2022","03-2023","03-2024","03-2025","5y Avg"],"R7":["Capex","0","22","0","1","0","5"],"R8":["% of Revenue","0%","5%","0%","0%","0%","1.1%"]},"da":{"R1":["Average useful life (years):",5],"R2":["(INR in millions)","Projections"],"R3":["","03-2026","03-2027","03-2028","03-2029","03-2030","03-2031","03-2032","03-2033","03-2034","03-2035"],"R4":["For CAPEX in"],"R19":["Total depreciation & amortization","6","2","3","3","4","4","5","5","5","5"],"R5":[2022,"4","","","","","","","","",""],"R6":[2023,"0","0","","","","","","","",""],"R7":[2024,"0","0","0","","","","","","",""],"R8":[2025,"0","0","0","0","","","","","",""],"R9":["2026","1","1","1","1","1","","","","",""],"R10":["2027","","1","1","1","1","1","","","",""],"R11":["2028","","","1","1","1","1","1","","",""],"R12":["2029","","","","1","1","1","1","1","",""],"R13":["2030","","","","","1","1","1","1","1",""],"R14":["2031","","","","","","1","1","1","1","1"],"R15":["2032","","","","","","","1","1","1","1"],"R16":["2033","","","","","","","","1","1","1"],"R17":["2034","","","","","","","","","1","1"],"R18":["2035","","","","","","","","","","1"]},"working_capital":{"R1":["(INR in millions except days)","Projections"],"R2":["","Historical Avg","03-2025","03-2026","03-2027","03-2028","03-2029","03-2030","03-2031","03-2032","03-2033","03-2034","03-2035"],"R3":["Days receivables","6","","6","5","4","5","4","4","4","4","4","4"],"R4":["Trade receivables","","0","6","5","4","5","5","5","5","5","5","6"],"R5":["Days payables","30","","30","35","35","33","35","34","34","34","34","34"],"R6":["Trade payables","","(30)","(23)","(26)","(26)","(24)","(25)","(25)","(25)","(26)","(26)","(26)"],"R7":["Days inventory","811","","811","648","727","729","701","719","716","712","716","715"],"R8":["Inventory","","543","614","485","547","531","500","518","521","533","541","551"],"R9":["Net working capital","","513","596","463","525","512","481","499","502","512","520","530"],"R10":["Change in NWC","","","83","(133)","61","(12)","(31)","18","3","11","8","9"]},"terminal":{"typical_5":["Terminal","44","(1)","4","49","2","4","6","37",4.25,"239"],"typical_10":["Terminal","77","(1)","5","83","3","5","9","65",9.25,"234"],"typical_ebitda_5":["Terminal","44","(1)","4","49","","","","",4.25,"518"],"typical_ebitda_10":["Terminal","77","(1)","5","83","","","","",9.25,"486"],"R1":["(INR in millions)","","3M/2026","2027","2028","2029","2030","2031","2032","2033","2034","2035"],"R2":["Profit before tax","","(0)","14","29","44","59","63","67","72","76","82"],"R3":["(-) Net interest income/expense","","(0)","(1)","(1)","(1)","(1)","(1)","(1)","(1)","(1)","(1)"],"R4":["(+) Depreciation & Armortization","","1","2","3","3","4","4","5","5","5","5"],"R5":["EBITDA","","2","17","33","49","64","69","73","78","82","88"],"R6":["(-) Tax","","(0)","1","1","2","2","2","3","3","3","3"],"R7":["(-) Capex","","1","4","4","4","5","5","5","5","5","5"],"R8":["(-) Change in NWC","","21","(133)","61","(12)","(31)","18","3","11","8","9"],"R9":["Free Cash Flow (FCF)","","(20)","145","(33)","55","89","44","62","60","66","70"],"R10":["Peers' EBITDA Multiples","17.6x"],"R11":["Terminal value",[["395","702"],["858","1,456"]]],"R12":["WACC / Discount rate","12.6%"],"R13":["Long-term growth rate","3.0%"],"R14":["Timing of FCF (mid year)","",0.12,0.75,1.75,2.75,3.75,4.75,5.75,6.75,7.75,8.75],"R15":["Present value of FCF","","(20)","133","(27)","39","57","25","31","27","27","25"],"R_end_5":{"R16":["Enterprise value","421"],"R17":["Projection period","182","43.3%"],"R18":["Terminal value","239","56.7%"],"R19":["(-) Current net debt","3"],"R20":["Equity value","418"],"R21":["(/) Outstanding shares","14"],"R22":["Fair price","29"],"TrueFair":[]},"R_end_10":{"R16":["Enterprise value","551"],"R17":["Projection period","317","57.5%"],"R18":["Terminal value","234","42.5%"],"R19":["(-) Current net debt","3"],"R20":["Equity value","548"],"R21":["(/) Outstanding shares","14"],"R22":["Fair price","38"],"TrueFair":[]},"R_end_ebitda_5":{"R16":["Enterprise value","701"],"R17":["Projection period","182","26.0%"],"R18":["Terminal value","518","74.0%"],"R19":["(-) Current net debt","3"],"R20":["Equity value","698"],"R21":["(/) Outstanding shares","14"],"R22":["Fair price","48"],"TrueFair":[]},"R_end_ebitda_10":{"R16":["Enterprise value","803"],"R17":["Projection period","317","39.4%"],"R18":["Terminal value","486","60.6%"],"R19":["(-) Current net debt","3"],"R20":["Equity value","800"],"R21":["(/) Outstanding shares","14"],"R22":["Fair price","55"],"TrueFair":[]}},"wacc":{"R1":["Category","Low","High"],"R2":["Long-term bond rate","6.9%","7.4%"],"R3":["Equity market risk premium","8.3%","9.3%"],"R4":["Adjusted beta",0.55,0.72],"R0":["Additional risk adjustments","0.0%","0.5%"],"R5":["Cost of equity","11.4%","14.5%"],"R6":["Tax rate","2.9%","7.9%"],"R7":["Debt/Equity ratio",0.08,0.08],"R8":["Cost of debt","7.5%","8.2%"],"R9":["After-tax WACC","11.1%","14.1%"],"R10":["Selected WACC","12.6%"]},"eps":[{"2025-03-31":-9.527},{"2024-03-31":24.172},{"2023-03-31":-39.053},{"2022-03-31":-3.4},{"2021-03-31":-48.4},{"2020-03-31":13}]},"variants":{"dcf-growth-exit-5y":{"gated_page":false,"data_available":true,"horizon_years":5,"terminal":{"method":"perpetuity_growth","perp_growth":0.03,"perp_growth_range":{"low":0.02,"high":0.04},"exit_multiple":null,"exit_year":4.25,"terminal_value_pv":239},"wacc_selected":0.126,"enterprise_value":421,"pv_projection":182,"pv_projection_pct":0.433,"pv_terminal":239,"pv_terminal_pct":0.5670000000000001,"net_debt":3,"equity_value":418,"shares_outstanding":14,"fair_value_per_share":28.881271,"fair_value_bridge_rounded":29,"upside_pct":0.4034,"sensitivity":{"fair_price_range":{"low":24.36,"high":36.44},"wacc_range":{"low":0.111,"high":0.141},"growth_range":{"low":0.02,"high":0.04},"exit_multiple_range":null,"terminal_value_grid":[["395","702"],["858","1,456"]]},"summary_squares":[40.3,"20.58","28.88"]},"dcf-growth-exit-10y":{"gated_page":true,"data_available":true,"horizon_years":10,"terminal":{"method":"perpetuity_growth","perp_growth":0.03,"perp_growth_range":{"low":0.02,"high":0.04},"exit_multiple":null,"exit_year":9.25,"terminal_value_pv":234},"wacc_selected":0.126,"enterprise_value":551,"pv_projection":317,"pv_projection_pct":0.575,"pv_terminal":234,"pv_terminal_pct":0.425,"net_debt":3,"equity_value":548,"shares_outstanding":14,"fair_value_per_share":37.849895,"fair_value_bridge_rounded":38,"upside_pct":0.8392,"sensitivity":{"fair_price_range":{"low":31.88,"high":47.7},"wacc_range":{"low":0.111,"high":0.141},"growth_range":{"low":0.02,"high":0.04},"exit_multiple_range":null,"terminal_value_grid":[["395","702"],["858","1,456"]]},"summary_squares":[83.9,"20.58","37.85"]},"dcf-ebitda-exit-5y":{"gated_page":true,"data_available":true,"horizon_years":5,"terminal":{"method":"exit_multiple","perp_growth":null,"perp_growth_range":null,"exit_multiple":17.6,"exit_year":4.25,"terminal_value_pv":518},"wacc_selected":0.126,"enterprise_value":701,"pv_projection":182,"pv_projection_pct":0.26,"pv_terminal":518,"pv_terminal_pct":0.74,"net_debt":3,"equity_value":698,"shares_outstanding":14,"fair_value_per_share":48.214058,"fair_value_bridge_rounded":48,"upside_pct":1.3428,"sensitivity":{"fair_price_range":{"low":36.49,"high":58.87},"wacc_range":{"low":0.111,"high":0.141},"growth_range":null,"exit_multiple_range":{"low":12.7,"high":21.4},"terminal_value_grid":[["395","702"],["858","1,456"]]},"summary_squares":[134.3,"20.58","48.21"]},"dcf-ebitda-exit-10y":{"gated_page":true,"data_available":true,"horizon_years":10,"terminal":{"method":"exit_multiple","perp_growth":null,"perp_growth_range":null,"exit_multiple":17.6,"exit_year":9.25,"terminal_value_pv":486},"wacc_selected":0.126,"enterprise_value":803,"pv_projection":317,"pv_projection_pct":0.39399999999999996,"pv_terminal":486,"pv_terminal_pct":0.606,"net_debt":3,"equity_value":800,"shares_outstanding":14,"fair_value_per_share":55.265533,"fair_value_bridge_rounded":55,"upside_pct":1.6854,"sensitivity":{"fair_price_range":{"low":42.04,"high":69.07},"wacc_range":{"low":0.111,"high":0.141},"growth_range":null,"exit_multiple_range":{"low":12.7,"high":21.4},"terminal_value_grid":[["395","702"],["858","1,456"]]},"summary_squares":[168.5,"20.58","55.27"]}},"other_valuations":{"epv_fair_price":8.576503,"ddm_stable_fair_price":-67.78189,"ddm_multi_fair_price":19.406082,"peter_lynch_fair_price":-38.26365,"trailing_pe":null,"forward_pe":null,"trailing_ev_ebitda":null},"source":{"carrier":"inline_script:window.most","url":"https://valueinvesting.io/PNC.NS/valuation/dcf-growth-exit-5y","fetched_via":"fetch","raw_ref":"https://valueinvesting.io/PNC.NS/valuation/dcf-growth-exit-5y"},"_debug":{"html_bytes":159199,"carrier_found":true,"field_count":63,"warnings":[],"variant_status":{"dcf-growth-exit-5y":"ok","dcf-growth-exit-10y":"ok","dcf-ebitda-exit-5y":"ok","dcf-ebitda-exit-10y":"ok"},"fetch_ms":31,"http_status":200}}