{"schema_version":"1.0.0","scraped_at":"2026-06-28T06:49:23.335Z","ticker":"TSFINV.NS","name":"TSF Investments Ltd","exchange":"National Stock Exchange of India","currency":"INR","country":"India","sector":"Auto Components","industry":"Administrative and Support and Waste Management and Remediation Services","as_of":"2026-03-31","price_current":396.75,"shares_outstanding":27.078766,"net_debt":-708.677,"market_cap":10743.5,"revenue_ttm":9848.903,"net_income_ttm":5217.768,"ebitda_current":1965.006,"eps_ttm":192.68901,"beta":null,"is_financial":false,"wacc":{"selected":0.16461122,"after_tax_range":{"low":0.146,"high":0.184},"build":{"long_term_bond_rate":{"low":0.069,"high":0.07400000000000001},"equity_risk_premium":{"low":0.083,"high":0.09300000000000001},"adjusted_beta":{"low":0.95,"high":1.13},"additional_risk_adjustment":{"low":0,"high":0.005},"cost_of_equity":{"low":0.147,"high":0.184},"tax_rate":{"low":0.27,"high":0.314},"debt_equity_ratio":{"low":0.02,"high":0.02},"cost_of_debt":{"low":0.075,"high":0.228}},"cost_of_equity_selected":0.16559881,"cost_of_debt_selected":0.15127599,"beta":null,"market_risk_premium":0.0831},"shared_projection":[{"year":2027,"revenue":10280,"pretax_profit":1884,"net_interest":0,"da":147,"ebitda":2031,"ebit":1884,"nopat":1304.848,"tax":579,"capex":454,"change_nwc":-2096,"fcf":3094,"timing":0.5,"discount_factor":0.926637,"pv_fcf":2867},{"year":2028,"revenue":10705,"pretax_profit":1961,"net_interest":0,"da":205,"ebitda":2167,"ebit":1962,"nopat":1358.871,"tax":603,"capex":472,"change_nwc":-79,"fcf":1170,"timing":1.5,"discount_factor":0.795662,"pv_fcf":931},{"year":2029,"revenue":11349,"pretax_profit":2080,"net_interest":0,"da":305,"ebitda":2385,"ebit":2080,"nopat":1440.597,"tax":639,"capex":501,"change_nwc":641,"fcf":603,"timing":2.5,"discount_factor":0.6832,"pv_fcf":412},{"year":2030,"revenue":11653,"pretax_profit":2135,"net_interest":0,"da":406,"ebitda":2541,"ebit":2135,"nopat":1478.69,"tax":656,"capex":514,"change_nwc":-567,"fcf":1938,"timing":3.5,"discount_factor":0.586633,"pv_fcf":1137},{"year":2031,"revenue":11965,"pretax_profit":2192,"net_interest":0,"da":494,"ebitda":2686,"ebit":2192,"nopat":1518.168,"tax":674,"capex":528,"change_nwc":37,"fcf":1448,"timing":4.5,"discount_factor":0.503716,"pv_fcf":729},{"year":2032,"revenue":12687,"pretax_profit":2325,"net_interest":0,"da":515,"ebitda":2840,"ebit":2325,"nopat":1610.283,"tax":715,"capex":560,"change_nwc":6,"fcf":1559,"timing":5.5,"discount_factor":0.432518,"pv_fcf":674},{"year":2033,"revenue":13128,"pretax_profit":2405,"net_interest":0,"da":537,"ebitda":2942,"ebit":2405,"nopat":1665.69,"tax":739,"capex":579,"change_nwc":-190,"fcf":1813,"timing":6.5,"discount_factor":0.371384,"pv_fcf":673},{"year":2034,"revenue":13867,"pretax_profit":2541,"net_interest":0,"da":559,"ebitda":3100,"ebit":2541,"nopat":1759.883,"tax":781,"capex":612,"change_nwc":-84,"fcf":1791,"timing":7.5,"discount_factor":0.318891,"pv_fcf":571},{"year":2035,"revenue":15243,"pretax_profit":2793,"net_interest":0,"da":590,"ebitda":3384,"ebit":2794,"nopat":1935.11,"tax":859,"capex":673,"change_nwc":-207,"fcf":2059,"timing":8.5,"discount_factor":0.273818,"pv_fcf":564},{"year":2036,"revenue":15649,"pretax_profit":2867,"net_interest":0,"da":623,"ebitda":3490,"ebit":2867,"nopat":1985.669,"tax":881,"capex":691,"change_nwc":-93,"fcf":2011,"timing":9.5,"discount_factor":0.235115,"pv_fcf":473}],"assumptions_raw":{"timing_dcf":[0.5,1.5,2.5,3.5,4.5,5.5,6.5,7.5,8.5,9.5],"sga_ratio":-0.30632345551580714,"RD_ratio":0,"interest_other_ratio":0.0025604882086867264,"tax_rate_dcf":0.30740531611719196,"avg_capex_ratio":0.044138152838448796,"past_capex":[-182.794,-1.98,-9.436,-88.392],"dr":[8.628451321474413,9.293677267508832,6.768633218218071,8.230253935733773,8.097521473820224,7.698802875924023,8.008859428492674,7.935061259412307,7.880907854609668,7.9416095141715495],"dp":[157.70948688666184,158.67062509125552,105.56572642136825,140.64861279976188,134.9616547707952,127.05866466397511,134.22297741151073,132.08109894876034,131.12091367474872,132.47499667833995],"di":[0,0,0,0,0,0,0,0,0,0],"current_nwc":59.933,"month_left":12,"net_interest_ratio":0,"rating":"AAA","current_reporting_period":"2026-03-31","current_FY_end":"2026-03-31","future_cogs_ratio":[-0.5130021079504996,-0.5130021079504996,-0.5130021079504996,-0.5130021079504996,-0.5130021079504996,-0.5130021079504996,-0.5130021079504996,-0.5130021079504996,-0.5130021079504996,-0.5130021079504996],"tax_good":1,"int_exp_ttm":10.488,"spread_excel":0.0059,"current_payout_ratio":-37.92282447207312,"global_cod":0.0644,"global_cod_no_finance":0.0644,"long_grow_arr":[0.005,0.015],"chosen_tax_arr":[0.30740531611719196,0.3412754520057649,0.21460447922252887,0.32503159202381715,0.20916446733477564],"cod1_good":"yes","cod2_good":"yes","chosen_6_past_debt":[21,36,31.874,182.511,179.05],"chosen_6_past_int":[3.691,3.855,11.844,10.9,10.488],"capex_9_years":[88.392,9.436,1.98,182.794,3.612,11.812,22.1,5.7,10.5],"low_add_coe":0,"high_add_coe":0.005,"add_cod2":0,"last_time":1782540549.5622907,"beta_peers":["ALICON.NS","GNA.NS","RACLGEAR.NS","508807.BO","515043.BO","JAYBARMARU.NS","538992.BO","MUNJALAU.NS","505163.BO","BOSCHLTD.NS"],"low_cod":0.07455,"high_cod":0.22800199272706864,"negative_coverage_ratio":0,"coe_arr":[0.14723543012281232,0.18396219941481373],"ddm_future_net_inc":[1304.6653150118932,1358.4906317798982,1440.3327256428602,1478.8797407577454,1518.4372189345459],"avg_long_growth":0.01,"normalized_earning":1844.7811085610185,"ttm_net_income_2_periods":[{"2026-03-31":5217.768},{"2025-12-31":4678.46}],"annual_net_debt_2_periods":[{"2026-03-31":-708.677},{"2025-09-30":2105.567}],"high_bond_yield":0.07365000000000001,"high_risk_premium":0.0931,"low_beta":0.9456730460025551,"high_beta":1.13117292604526,"coe":0.16559881476881302,"avg_tax":0.29237040391958435,"tax_arr":[0.2702849813593267,0.31445582647984205],"low_d_e":0.0166658910038628,"effective_interest_rate":0.22800199272706864,"synthetic_ratings_cod":0.07455,"avg_cod":0.15127599636353434,"selected_wacc":0.16461122115003546,"wacc_arr":[0.14571361166739136,0.1835088306326796],"beta":null,"ebit_ttm":1804.8629999999998},"model_tables":{"revenue":{"R1":["(INR in millions)","Projections"],"R2":["","03-2026","03-2027","03-2028","03-2029","03-2030","03-2031","03-2032","03-2033","03-2034","03-2035","03-2036"],"R3":["Revenue","9,849","10,280","10,705","11,349","11,653","11,965","12,687","13,128","13,867","15,243","15,649"],"R4":["% Growth","537%","4%","4%","6%","3%","3%","6%","3%","6%","10%","3%"],"R5":["Cost of goods sold","(5,053)","(5,274)","(5,491)","(5,822)","(5,978)","(6,138)","(6,509)","(6,734)","(7,114)","(7,820)","(8,028)"],"R6":["% of Revenue","51%","51%","51%","51%","51%","51%","51%","51%","51%","51%","51%"],"R7":["Selling, G&A expenses","(3,017)","(3,149)","(3,279)","(3,477)","(3,570)","(3,665)","(3,886)","(4,021)","(4,248)","(4,669)","(4,794)"],"R8":["% of Revenue","31%","31%","31%","31%","31%","31%","31%","31%","31%","31%","31%"],"R9":["Research & Development","0","0","0","0","0","0","0","0","0","0","0"],"R10":["% of Revenue","0%","0%","0%","0%","0%","0%","0%","0%","0%","0%","0%"],"R11":["Net interest & other expenses","25","26","27","29","30","31","32","34","36","39","40"],"R12":["% of Revenue","0%","0%","0%","0%","0%","0%","0%","0%","0%","0%","0%"],"R13":["Tax expense","(555)","(579)","(603)","(639)","(656)","(674)","(715)","(739)","(781)","(859)","(881)"],"R14":["Tax rate","31%","31%","31%","31%","31%","31%","31%","31%","31%","31%","31%"],"R15":["Net profit","1,250","1,305","1,358","1,440","1,479","1,518","1,610","1,666","1,760","1,935","1,986"],"R16":["% Margin","13%","13%","13%","13%","13%","13%","13%","13%","13%","13%","13%"]},"capex":{"R1":["(INR in millions)","Projections"],"R2":["","03-2027","03-2028","03-2029","03-2030","03-2031","03-2032","03-2033","03-2034","03-2035","03-2036"],"R3":["Capex","454","472","501","514","528","560","579","612","673","691"],"R4":["% of Revenue","4%","4%","4%","4%","4%","4%","4%","4%","4%","4%"],"R5":["Historical"],"R6":["","03-2022","03-2023","03-2024","03-2025","03-2026","5y Avg"],"R7":["Capex","4","183","2","9","88","57"],"R8":["% of Revenue","0%","20%","0%","1%","1%","4.4%"]},"da":{"R1":["Average useful life (years):",5],"R2":["(INR in millions)","Projections"],"R3":["","03-2027","03-2028","03-2029","03-2030","03-2031","03-2032","03-2033","03-2034","03-2035","03-2036"],"R4":["For CAPEX in"],"R19":["Total depreciation & amortization","147","205","305","406","494","515","537","559","590","623"],"R5":[2023,"37","","","","","","","","",""],"R6":[2024,"0","0","","","","","","","",""],"R7":[2025,"2","2","2","","","","","","",""],"R8":[2026,"18","18","18","18","","","","","",""],"R9":["2027","91","91","91","91","91","","","","",""],"R10":["2028","","94","94","94","94","94","","","",""],"R11":["2029","","","100","100","100","100","100","","",""],"R12":["2030","","","","103","103","103","103","103","",""],"R13":["2031","","","","","106","106","106","106","106",""],"R14":["2032","","","","","","112","112","112","112","112"],"R15":["2033","","","","","","","116","116","116","116"],"R16":["2034","","","","","","","","122","122","122"],"R17":["2035","","","","","","","","","135","135"],"R18":["2036","","","","","","","","","","138"]},"working_capital":{"R1":["(INR in millions except days)","Projections"],"R2":["","Historical Avg","03-2026","03-2027","03-2028","03-2029","03-2030","03-2031","03-2032","03-2033","03-2034","03-2035","03-2036"],"R3":["Days receivables","9","","9","9","7","8","8","8","8","8","8","8"],"R4":["Trade receivables","","64","243","273","210","263","265","268","288","301","329","340"],"R5":["Days payables","158","","158","159","106","141","135","127","134","132","131","132"],"R6":["Trade payables","","(4)","(2,279)","(2,387)","(1,684)","(2,304)","(2,270)","(2,266)","(2,476)","(2,574)","(2,809)","(2,914)"],"R7":["Days inventory","0","","0","0","0","0","0","0","0","0","0","0"],"R8":["Inventory","","0","0","0","0","0","0","0","0","0","0","0"],"R9":["Net working capital","","60","(2,036)","(2,115)","(1,473)","(2,041)","(2,004)","(1,998)","(2,188)","(2,273)","(2,480)","(2,573)"],"R10":["Change in NWC","","","(2,096)","(79)","641","(567)","37","6","(190)","(84)","(207)","(93)"]},"terminal":{"typical_5":["Terminal","2,136","0","402","2,537","657","514","37","1,330",5,"4,054"],"typical_10":["Terminal","2,734","0","591","3,325","840","659","(128)","1,954",10,"2,781"],"typical_ebitda_5":["Terminal","2,136",0,"402","2,537","","","","",5,"9,949"],"typical_ebitda_10":["Terminal","2,734",0,"591","3,325","","","","",10,"6,084"],"R1":["(INR in millions)","","2027","2028","2029","2030","2031","2032","2033","2034","2035","2036"],"R2":["Profit before tax","","1,884","1,961","2,080","2,135","2,192","2,325","2,405","2,541","2,793","2,867"],"R3":["(-) Net interest income/expense","","0","0","0","0","0","0","0","0","0","0"],"R4":["(+) Depreciation & Armortization","","147","205","305","406","494","515","537","559","590","623"],"R5":["EBITDA","","2,031","2,167","2,385","2,541","2,686","2,840","2,942","3,100","3,384","3,490"],"R6":["(-) Tax","","579","603","639","656","674","715","739","781","859","881"],"R7":["(-) Capex","","454","472","501","514","528","560","579","612","673","691"],"R8":["(-) Change in NWC","","(2,096)","(79)","641","(567)","37","6","(190)","(84)","(207)","(93)"],"R9":["Free Cash Flow (FCF)","","3,094","1,170","603","1,938","1,448","1,559","1,813","1,791","2,059","2,011"],"R10":["Peers' EBITDA Multiples","8.4x"],"R11":["Terminal value",[["8,685","12,764"],["21,314","27,927"]]],"R12":["WACC / Discount rate","16.5%"],"R13":["Long-term growth rate","1.0%"],"R14":["Timing of FCF (mid year)","",0.5,1.5,2.5,3.5,4.5,5.5,6.5,7.5,8.5,9.5],"R15":["Present value of FCF","","2,867","931","412","1,137","729","674","673","571","564","473"],"R_end_5":{"R16":["Enterprise value","10,130"],"R17":["Projection period","6,076","60.0%"],"R18":["Terminal value","4,054","40.0%"],"R19":["(-) Current net debt","(709)"],"R20":["Equity value","10,839"],"R21":["(/) Outstanding shares","27"],"R22":["Fair price","400"],"TrueFair":[]},"R_end_10":{"R16":["Enterprise value","11,813"],"R17":["Projection period","9,032","76.5%"],"R18":["Terminal value","2,781","23.5%"],"R19":["(-) Current net debt","(709)"],"R20":["Equity value","12,521"],"R21":["(/) Outstanding shares","27"],"R22":["Fair price","462"],"TrueFair":[]},"R_end_ebitda_5":{"R16":["Enterprise value","16,025"],"R17":["Projection period","6,076","37.9%"],"R18":["Terminal value","9,949","62.1%"],"R19":["(-) Current net debt","(709)"],"R20":["Equity value","16,733"],"R21":["(/) Outstanding shares","27"],"R22":["Fair price","618"],"TrueFair":[]},"R_end_ebitda_10":{"R16":["Enterprise value","15,116"],"R17":["Projection period","9,032","59.7%"],"R18":["Terminal value","6,084","40.3%"],"R19":["(-) Current net debt","(709)"],"R20":["Equity value","15,825"],"R21":["(/) Outstanding shares","27"],"R22":["Fair price","584"],"TrueFair":[]}},"wacc":{"R1":["Category","Low","High"],"R2":["Long-term bond rate","6.9%","7.4%"],"R3":["Equity market risk premium","8.3%","9.3%"],"R4":["Adjusted beta",0.95,1.13],"R0":["Additional risk adjustments","0.0%","0.5%"],"R5":["Cost of equity","14.7%","18.4%"],"R6":["Tax rate","27.0%","31.4%"],"R7":["Debt/Equity ratio",0.02,0.02],"R8":["Cost of debt","7.5%","22.8%"],"R9":["After-tax WACC","14.6%","18.4%"],"R10":["Selected WACC","16.5%"]},"eps":[{"2026-03-31":5217.768},{"2025-03-31":4121.029},{"2024-03-31":5331.443},{"2023-03-31":2375.561},{"2022-03-31":1631.878},{"2021-03-31":738.788}]},"variants":{"dcf-growth-exit-5y":{"gated_page":false,"data_available":true,"horizon_years":5,"terminal":{"method":"perpetuity_growth","perp_growth":0.01,"perp_growth_range":{"low":0.005,"high":0.015},"exit_multiple":null,"exit_year":5,"terminal_value_pv":4054},"wacc_selected":0.165,"enterprise_value":10130,"pv_projection":6076,"pv_projection_pct":0.6,"pv_terminal":4054,"pv_terminal_pct":0.4,"net_debt":-709,"equity_value":10839,"shares_outstanding":27,"fair_value_per_share":400.26196,"fair_value_bridge_rounded":400,"upside_pct":0.0089,"sensitivity":{"fair_price_range":{"low":363.15,"high":450.57},"wacc_range":{"low":0.146,"high":0.184},"growth_range":{"low":0.005,"high":0.015},"exit_multiple_range":null,"terminal_value_grid":[["8,685","12,764"],["21,314","27,927"]]},"summary_squares":[0.9,"396.75","400.26"]},"dcf-growth-exit-10y":{"gated_page":true,"data_available":true,"horizon_years":10,"terminal":{"method":"perpetuity_growth","perp_growth":0.01,"perp_growth_range":{"low":0.005,"high":0.015},"exit_multiple":null,"exit_year":10,"terminal_value_pv":2781},"wacc_selected":0.165,"enterprise_value":11813,"pv_projection":9032,"pv_projection_pct":0.765,"pv_terminal":2781,"pv_terminal_pct":0.235,"net_debt":-709,"equity_value":12521,"shares_outstanding":27,"fair_value_per_share":462.40662,"fair_value_bridge_rounded":462,"upside_pct":0.1655,"sensitivity":{"fair_price_range":{"low":416.49,"high":524.3},"wacc_range":{"low":0.146,"high":0.184},"growth_range":{"low":0.005,"high":0.015},"exit_multiple_range":null,"terminal_value_grid":[["8,685","12,764"],["21,314","27,927"]]},"summary_squares":[16.5,"396.75","462.41"]},"dcf-ebitda-exit-5y":{"gated_page":true,"data_available":true,"horizon_years":5,"terminal":{"method":"exit_multiple","perp_growth":null,"perp_growth_range":null,"exit_multiple":8.4,"exit_year":5,"terminal_value_pv":9949},"wacc_selected":0.165,"enterprise_value":16025,"pv_projection":6076,"pv_projection_pct":0.379,"pv_terminal":9949,"pv_terminal_pct":0.621,"net_debt":-709,"equity_value":16733,"shares_outstanding":27,"fair_value_per_share":617.94946,"fair_value_bridge_rounded":618,"upside_pct":0.5575,"sensitivity":{"fair_price_range":{"low":560.49,"high":690.33},"wacc_range":{"low":0.146,"high":0.184},"growth_range":null,"exit_multiple_range":{"low":7.8,"high":9.1},"terminal_value_grid":[["8,685","12,764"],["21,314","27,927"]]},"summary_squares":[55.8,"396.75","617.95"]},"dcf-ebitda-exit-10y":{"gated_page":true,"data_available":true,"horizon_years":10,"terminal":{"method":"exit_multiple","perp_growth":null,"perp_growth_range":null,"exit_multiple":8.4,"exit_year":10,"terminal_value_pv":6084},"wacc_selected":0.165,"enterprise_value":15116,"pv_projection":9032,"pv_projection_pct":0.597,"pv_terminal":6084,"pv_terminal_pct":0.40299999999999997,"net_debt":-709,"equity_value":15825,"shares_outstanding":27,"fair_value_per_share":584.40076,"fair_value_bridge_rounded":584,"upside_pct":0.473,"sensitivity":{"fair_price_range":{"low":519.67,"high":667.84},"wacc_range":{"low":0.146,"high":0.184},"growth_range":null,"exit_multiple_range":{"low":7.8,"high":9.1},"terminal_value_grid":[["8,685","12,764"],["21,314","27,927"]]},"summary_squares":[47.3,"396.75","584.40"]}},"other_valuations":{"epv_fair_price":445.55948,"ddm_stable_fair_price":1032.5692,"ddm_multi_fair_price":248.84555,"peter_lynch_fair_price":4817.225,"trailing_pe":2.0590215,"forward_pe":8.23465,"trailing_ev_ebitda":null},"source":{"carrier":"inline_script:window.most","url":"https://valueinvesting.io/TSFINV.NS/valuation/dcf-growth-exit-5y","fetched_via":"fetch","raw_ref":"https://valueinvesting.io/TSFINV.NS/valuation/dcf-growth-exit-5y"},"_debug":{"html_bytes":123633,"carrier_found":true,"field_count":60,"warnings":[],"variant_status":{"dcf-growth-exit-5y":"ok","dcf-growth-exit-10y":"ok","dcf-ebitda-exit-5y":"ok","dcf-ebitda-exit-10y":"ok"},"fetch_ms":81,"http_status":200},"relative":{"peers_pe":["TSFINV.NS","ALICON.NS","GNA.NS","RACLGEAR.NS","RICOAUTO.NS","STERTOOLS.NS","508807.BO","515043.BO","JAYBARMARU.NS","MUNJALAU.NS"],"peers_ev":["TSFINV.NS","ALICON.NS","GNA.NS","RACLGEAR.NS","RICOAUTO.NS","STERTOOLS.NS","508807.BO","515043.BO","JAYBARMARU.NS","505163.BO"],"forward_pe":8.23465,"trailing_pe":2.0590215,"forward_ev_ebitda":null,"trailing_ev_ebitda":null,"forward_ebitda":2031.008,"current_ebitda":1965.006}}